httpprint/__init__.py
httpprint/test.py
httpprint-1.3.dist-info/licenses/LICENSE
httpprint-1.3.dist-info/METADATA
httpprint-1.3.dist-info/WHEEL
httpprint-1.3.dist-info/top_level.txt
httpprint-1.3.dist-info/RECORD
