Metadata-Version: 2.4
Name: httpprint
Version: 1.3
Summary: A minimal package allowing printing to a http server and the console insted of just the console. Great for monitoring long running scripts!
Author-email: Sl1ceOfToast <robertescheer@gmail.com>
License-Expression: MIT
Project-URL: Homepage, https://github.com/Ungetoastet/httpprint
Project-URL: Issues, https://github.com/Ungetoastet/httpprint/issues
Classifier: Programming Language :: Python :: 3
Classifier: Operating System :: OS Independent
Requires-Python: >=3.9
License-File: LICENSE
Requires-Dist: flask
Requires-Dist: logging
Dynamic: license-file
